novamiko.py
setup.py
novamiko.egg-info/PKG-INFO
novamiko.egg-info/SOURCES.txt
novamiko.egg-info/dependency_links.txt
novamiko.egg-info/pbr.json
novamiko.egg-info/requires.txt
novamiko.egg-info/top_level.txt