Metadata-Version: 1.1
Name: novamiko
Version: 0.0.4
Summary: Wrapper around Openstack Nova and Paramiko
Home-page: https://github.com/rackerlabs/novamiko
Author: Andrew Melton
Author-email: andrew.melton@rackspace.com
License: Apache
Keywords: openstack nova paramiko
Platform: UNKNOWN
Classifier: Development Status :: 3 - Alpha
Classifier: Topic :: Utilities
